mzx/__init__.py
mzx/cli.py
mzx/docker.py
mzx/gui.py
mzx/types.py
mzx/vendor.py
mzx-0.3.1.dist-info/AUTHORS.rst
mzx-0.3.1.dist-info/LICENSE
mzx-0.3.1.dist-info/METADATA
mzx-0.3.1.dist-info/WHEEL
mzx-0.3.1.dist-info/entry_points.txt
mzx-0.3.1.dist-info/top_level.txt
mzx-0.3.1.dist-info/RECORD
