Metadata-Version: 2.1
Name: mzx
Version: 0.3.1
Summary: Easy to use Mass Spec conversion utility
Author-email: Michael Freitas <mike@massmatrix.bio>
Maintainer-email: Herman Singh <herman@massmatrix.bio>, MassMatrix <eng@massmatrix.bio>
License: GNU GENERAL PUBLIC LICENSE
Project-URL: Documentation, https://readthedocs.org/projects/mzx
Project-URL: Source Code, https://github.com/mass-matrix/mzx
Project-URL: Issue Tracker, https://github.com/mass-matrix/mzx/issues
Keywords: mass spectrometry,conversion,bioinformatics
Classifier: Development Status :: 4 - Beta
Classifier: Intended Audience :: Developers
Classifier: Intended Audience :: Science/Research
Classifier: License :: OSI Approved :: GNU General Public License v3 (GPLv3)
Classifier: Natural Language :: English
Classifier: Operating System :: MacOS :: MacOS X
Classifier: Operating System :: Microsoft :: Windows
Classifier: Operating System :: POSIX :: Linux
Classifier: Programming Language :: Python :: 3.12
Classifier: Programming Language :: Python :: 3.11
Classifier: Programming Language :: Python :: 3.10
Classifier: Topic :: File Formats
Classifier: Topic :: Scientific/Engineering
Classifier: Topic :: Scientific/Engineering :: Chemistry
Classifier: Topic :: Software Development
Requires-Python: >=3.10
License-File: LICENSE
License-File: AUTHORS.rst
Requires-Dist: loguru >=0.5.0
Requires-Dist: lxml >=4.6.0
Requires-Dist: pyside6 >=6.0
